LXST/Common.py
LXST/Filters.c
LXST/Filters.h
LXST/Filters.py
LXST/Generators.py
LXST/Mixer.py
LXST/Network.py
LXST/Pipeline.py
LXST/Processing.py
LXST/Sinks.py
LXST/Sources.py
LXST/__init__.py
LXST/_version.py
LXST/filterlib.cpython-311-aarch64-linux-gnu.so
LXST/filterlib.cpython-311-darwin.so
LXST/filterlib.cpython-311-x86_64-linux-gnu.so
LXST/filterlib.cpython-312-aarch64-linux-gnu.so
LXST/filterlib.cpython-312-darwin.so
LXST/filterlib.cpython-312-x86_64-linux-gnu.so
LXST/filterlib.cpython-313-aarch64-linux-gnu.so
LXST/filterlib.cpython-313-darwin.so
LXST/filterlib.cpython-313-x86_64-linux-gnu.so
LXST/filterlib.cpython-314-aarch64-linux-gnu.so
LXST/filterlib.cpython-314-darwin.so
LXST/filterlib.cpython-314-x86_64-linux-gnu.so
LXST/filterlib.dll
LXST/Codecs/Codec.py
LXST/Codecs/Codec2.py
LXST/Codecs/Opus.py
LXST/Codecs/Raw.py
LXST/Codecs/__init__.py
LXST/Codecs/libs/pydub/__init__.py
LXST/Codecs/libs/pydub/audio_segment.py
LXST/Codecs/libs/pydub/effects.py
LXST/Codecs/libs/pydub/exceptions.py
LXST/Codecs/libs/pydub/generators.py
LXST/Codecs/libs/pydub/logging_utils.py
LXST/Codecs/libs/pydub/playback.py
LXST/Codecs/libs/pydub/pyaudioop.py
LXST/Codecs/libs/pydub/scipy_effects.py
LXST/Codecs/libs/pydub/silence.py
LXST/Codecs/libs/pydub/utils.py
LXST/Codecs/libs/pyogg/__init__.py
LXST/Codecs/libs/pyogg/audio_file.py
LXST/Codecs/libs/pyogg/flac.py
LXST/Codecs/libs/pyogg/flac_file.py
LXST/Codecs/libs/pyogg/flac_file_stream.py
LXST/Codecs/libs/pyogg/library_loader.py
LXST/Codecs/libs/pyogg/ogg.py
LXST/Codecs/libs/pyogg/ogg_opus_writer.py
LXST/Codecs/libs/pyogg/opus.py
LXST/Codecs/libs/pyogg/opus_buffered_encoder.py
LXST/Codecs/libs/pyogg/opus_decoder.py
LXST/Codecs/libs/pyogg/opus_encoder.py
LXST/Codecs/libs/pyogg/opus_file.py
LXST/Codecs/libs/pyogg/opus_file_stream.py
LXST/Codecs/libs/pyogg/py.typed
LXST/Codecs/libs/pyogg/pyogg_error.py
LXST/Codecs/libs/pyogg/vorbis.py
LXST/Codecs/libs/pyogg/vorbis_file.py
LXST/Codecs/libs/pyogg/vorbis_file_stream.py
lxst-0.4.6.dist-info/licenses/LICENSE
lxst-0.4.6.dist-info/METADATA
lxst-0.4.6.dist-info/WHEEL
lxst-0.4.6.dist-info/entry_points.txt
lxst-0.4.6.dist-info/top_level.txt
lxst-0.4.6.dist-info/RECORD
