Metadata-Version: 2.4
Name: lxst
Version: 0.4.6
Summary: Lightweight Extensible Signal Transport for Reticulum
Home-page: https://git.unsigned.io/markqvist/lxst
Author: Mark Qvist
Author-email: mark@unsigned.io
Classifier: Programming Language :: Python :: 3
Classifier: License :: Other/Proprietary License
Classifier: Operating System :: OS Independent
Requires-Python: >=3.11
License-File: LICENSE
Requires-Dist: rns>=1.0.4
Requires-Dist: lxmf>=0.9.3
Requires-Dist: numpy>=2.3.4
Requires-Dist: pycodec2>=4.1.0
Requires-Dist: audioop-lts>=0.2.1; python_version >= "3.13"
Requires-Dist: cffi>=2.0.0
Dynamic: author
Dynamic: author-email
Dynamic: classifier
Dynamic: description
Dynamic: description-content-type
Dynamic: home-page
Dynamic: license-file
Dynamic: requires-dist
Dynamic: requires-python
Dynamic: summary
